[{"Id":"1","Group":"1","Type":"1","DmgType":"2","Name":"灼烧","Display":"Burn","Duration":"7","Interval":"0.5","Value":"5","ParamValue":"0"},{"Id":"2","Group":"2","Type":"2","DmgType":"2","Name":"潮湿","Display":"Wet","Duration":"7","Interval":"0","Value":"0","ParamValue":"6"},{"Id":"3","Group":"3","Type":"3","DmgType":"2","Name":"寒冷","Display":"Frosted","Duration":"4","Interval":"0","Value":"0.6","ParamValue":"7"},{"Id":"4","Group":"4","Type":"4","DmgType":"2","Name":"冰冻","Display":"Frozen","Duration":"3","Interval":"0","Value":"0","ParamValue":"0"},{"Id":"5","Group":"5","Type":"5","DmgType":"2","Name":"加速","Display":"Speed","Duration":"12","Interval":"0","Value":"0.5","ParamValue":"0"},{"Id":"6","Group":"6","Type":"6","DmgType":"2","Name":"汽化","Display":"Steam","Duration":"0.6","Interval":"0","Value":"0","ParamValue":"0"},{"Id":"7","Group":"7","Type":"7","DmgType":"2","Name":"解冻","Display":"DeFrozen","Duration":"0.6","Interval":"0","Value":"0","ParamValue":"0"},{"Id":"8","Group":"8","Type":"8","DmgType":"1","Name":"火抗","Display":"","Duration":"7","Interval":"0","Value":"0.5","ParamValue":"1"},{"Id":"9","Group":"8","Type":"8","DmgType":"1","Name":"火抗+1","Display":"","Duration":"10","Interval":"0","Value":"0.35","ParamValue":"1"},{"Id":"10","Group":"8","Type":"8","DmgType":"1","Name":"火抗+2","Display":"","Duration":"15","Interval":"0","Value":"0.2","ParamValue":"1"},{"Id":"11","Group":"8","Type":"9","DmgType":"1","Name":"水抗","Display":"","Duration":"7","Interval":"0","Value":"0.5","ParamValue":"2"},{"Id":"12","Group":"8","Type":"9","DmgType":"1","Name":"水抗+1","Display":"","Duration":"10","Interval":"0","Value":"0.35","ParamValue":"2"},{"Id":"13","Group":"8","Type":"9","DmgType":"1","Name":"水抗+2","Display":"","Duration":"15","Interval":"0","Value":"0.2","ParamValue":"2"},{"Id":"14","Group":"8","Type":"10","DmgType":"1","Name":"地抗","Display":"","Duration":"7","Interval":"0","Value":"0.5","ParamValue":"3"},{"Id":"15","Group":"8","Type":"10","DmgType":"1","Name":"地抗+1","Display":"","Duration":"10","Interval":"0","Value":"0.35","ParamValue":"3"},{"Id":"16","Group":"8","Type":"10","DmgType":"1","Name":"地抗+2","Display":"","Duration":"15","Interval":"0","Value":"0.2","ParamValue":"3"},{"Id":"17","Group":"8","Type":"11","DmgType":"1","Name":"电抗","Display":"","Duration":"7","Interval":"0","Value":"0.5","ParamValue":"4"},{"Id":"18","Group":"8","Type":"11","DmgType":"1","Name":"电抗+1","Display":"","Duration":"10","Interval":"0","Value":"0.35","ParamValue":"4"},{"Id":"19","Group":"8","Type":"11","DmgType":"1","Name":"电抗+2","Display":"","Duration":"15","Interval":"0","Value":"0.2","ParamValue":"4"},{"Id":"20","Group":"8","Type":"12","DmgType":"1","Name":"寒抗","Display":"","Duration":"7","Interval":"0","Value":"0.5","ParamValue":"5"},{"Id":"21","Group":"8","Type":"12","DmgType":"1","Name":"寒抗+1","Display":"","Duration":"10","Interval":"0","Value":"0.35","ParamValue":"5"},{"Id":"22","Group":"8","Type":"12","DmgType":"1","Name":"寒抗+2","Display":"","Duration":"15","Interval":"0","Value":"0.2","ParamValue":"5"},{"Id":"23","Group":"9","Type":"13","DmgType":"1","Name":"击冰","Display":"","Duration":"0","Interval":"0","Value":"2","ParamValue":"4"},{"Id":"24","Group":"10","Type":"14","DmgType":"1","Name":"破冰","Display":"DeFrozen","Duration":"0.6","Interval":"0","Value":"0","ParamValue":"0"},{"Id":"25","Group":"11","Type":"15","DmgType":"2","Name":"麻痹","Display":"","Duration":"0.1","Interval":"0","Value":"0","ParamValue":"0"},{"Id":"26","Group":"12","Type":"16","DmgType":"2","Name":"中毒","Display":"poisonBuff","Duration":"7","Interval":"1","Value":"10","ParamValue":"0"},{"Id":"27","Group":"13","Type":"17","DmgType":"2","Name":"眩晕","Display":"Stun","Duration":"4","Interval":"0","Value":"0","ParamValue":"0"},{"Id":"28","Group":"14","Type":"18","DmgType":"2","Name":"混乱","Display":"","Duration":"10","Interval":"0","Value":"0","ParamValue":"0"},{"Id":"29","Group":"15","Type":"19","DmgType":"2","Name":"泥泞","Display":"mudBuff","Duration":"7","Interval":"0","Value":"0.6","ParamValue":"0"},{"Id":"30","Group":"16","Type":"20","DmgType":"1","Name":"击退","Display":"","Duration":"0","Interval":"0","Value":"1","ParamValue":"0"},{"Id":"31","Group":"17","Type":"21","DmgType":"1","Name":"击破","Display":"","Duration":"0","Interval":"0","Value":"0","ParamValue":"0"},{"Id":"32","Group":"0","Type":"22","DmgType":"1","Name":"击泥","Display":"","Duration":"0","Interval":"0","Value":"2","ParamValue":"29"}]